[
    {
        "id": 2,
        "title": "Lorem ipsum dolor sit amet",
        "path": "lorem-ipsum-dolor-sit-amet-2",
        "content": "{\"blocks\":[{\"key\":\"7pffo\",\"text\":\"\",\"type\":\"unstyled\",\"depth\":0,\"inlineStyleRanges\":[],\"entityRanges\":[],\"data\":{}},{\"key\":\"8kpm4\",\"text\":\" \",\"type\":\"atomic\",\"depth\":0,\"inlineStyleRanges\":[],\"entityRanges\":[{\"offset\":0,\"length\":1,\"key\":0}],\"data\":{}},{\"key\":\"b1g62\",\"text\":\"\",\"type\":\"unstyled\",\"depth\":0,\"inlineStyleRanges\":[],\"entityRanges\":[],\"data\":{}},{\"key\":\"69s70\",\"text\":\" \",\"type\":\"atomic\",\"depth\":0,\"inlineStyleRanges\":[],\"entityRanges\":[{\"offset\":0,\"length\":1,\"key\":1}],\"data\":{}},{\"key\":\"1avts\",\"text\":\"\",\"type\":\"unstyled\",\"depth\":0,\"inlineStyleRanges\":[],\"entityRanges\":[],\"data\":{}}],\"entityMap\":{}}",
        "created_at": "2021-04-14T11:10:17.116172Z",
        "published": false,
        "featured": true,
        "banner_link": "https://source.unsplash.com/random",
        "font_banner": "Lorem ipsum dolor sit amet"
    },
    {
        "id": 3,
        "title": "Lorem ipsum dolor sit amet",
        "path": "lorem-ipsum-dolor-sit-amet-3",
        "content": "{\"blocks\":[{\"key\":\"7pffo\",\"text\":\"\",\"type\":\"unstyled\",\"depth\":0,\"inlineStyleRanges\":[],\"entityRanges\":[],\"data\":{}},{\"key\":\"8kpm4\",\"text\":\" \",\"type\":\"atomic\",\"depth\":0,\"inlineStyleRanges\":[],\"entityRanges\":[{\"offset\":0,\"length\":1,\"key\":0}],\"data\":{}},{\"key\":\"b1g62\",\"text\":\"\",\"type\":\"unstyled\",\"depth\":0,\"inlineStyleRanges\":[],\"entityRanges\":[],\"data\":{}},{\"key\":\"69s70\",\"text\":\" \",\"type\":\"atomic\",\"depth\":0,\"inlineStyleRanges\":[],\"entityRanges\":[{\"offset\":0,\"length\":1,\"key\":1}],\"data\":{}},{\"key\":\"1avts\",\"text\":\"\",\"type\":\"unstyled\",\"depth\":0,\"inlineStyleRanges\":[],\"entityRanges\":[],\"data\":{}}],\"entityMap\":{}}",
        "created_at": "2021-04-14T11:10:17.116172Z",
        "published": false,
        "featured": false,
        "banner_link": "https://source.unsplash.com/random",
        "font_banner": "Lorem ipsum dolor sit amet"
    },
    {
        "id": 4,
        "title": "Lorem ipsum dolor sit amet",
        "path": "lorem-ipsum-dolor-sit-amet-4",
        "content": "{\"blocks\":[{\"key\":\"7pffo\",\"text\":\"\",\"type\":\"unstyled\",\"depth\":0,\"inlineStyleRanges\":[],\"entityRanges\":[],\"data\":{}},{\"key\":\"8kpm4\",\"text\":\" \",\"type\":\"atomic\",\"depth\":0,\"inlineStyleRanges\":[],\"entityRanges\":[{\"offset\":0,\"length\":1,\"key\":0}],\"data\":{}},{\"key\":\"b1g62\",\"text\":\"\",\"type\":\"unstyled\",\"depth\":0,\"inlineStyleRanges\":[],\"entityRanges\":[],\"data\":{}},{\"key\":\"69s70\",\"text\":\" \",\"type\":\"atomic\",\"depth\":0,\"inlineStyleRanges\":[],\"entityRanges\":[{\"offset\":0,\"length\":1,\"key\":1}],\"data\":{}},{\"key\":\"1avts\",\"text\":\"\",\"type\":\"unstyled\",\"depth\":0,\"inlineStyleRanges\":[],\"entityRanges\":[],\"data\":{}}],\"entityMap\":{}}",
        "created_at": "2021-04-14T11:10:17.116172Z",
        "published": false,
        "featured": false,
        "banner_link": "https://source.unsplash.com/random",
        "font_banner": "Lorem ipsum dolor sit amet"
    },
    {
        "id": 5,
        "title": "Lorem ipsum dolor sit amet",
        "path": "lorem-ipsum-dolor-sit-amet-5",
        "content": "{\"blocks\":[{\"key\":\"7pffo\",\"text\":\"\",\"type\":\"unstyled\",\"depth\":0,\"inlineStyleRanges\":[],\"entityRanges\":[],\"data\":{}},{\"key\":\"8kpm4\",\"text\":\" \",\"type\":\"atomic\",\"depth\":0,\"inlineStyleRanges\":[],\"entityRanges\":[{\"offset\":0,\"length\":1,\"key\":0}],\"data\":{}},{\"key\":\"b1g62\",\"text\":\"\",\"type\":\"unstyled\",\"depth\":0,\"inlineStyleRanges\":[],\"entityRanges\":[],\"data\":{}},{\"key\":\"69s70\",\"text\":\" \",\"type\":\"atomic\",\"depth\":0,\"inlineStyleRanges\":[],\"entityRanges\":[{\"offset\":0,\"length\":1,\"key\":1}],\"data\":{}},{\"key\":\"1avts\",\"text\":\"\",\"type\":\"unstyled\",\"depth\":0,\"inlineStyleRanges\":[],\"entityRanges\":[],\"data\":{}}],\"entityMap\":{}}",
        "created_at": "2021-04-14T11:10:17.116172Z",
        "published": false,
        "featured": false,
        "banner_link": "https://source.unsplash.com/random",
        "font_banner": "Lorem ipsum dolor sit amet"
    },
    {
        "id": 6,
        "title": "Lorem ipsum dolor sit amet",
        "path": "lorem-ipsum-dolor-sit-amet-6",
        "content": "{\"blocks\":[{\"key\":\"7pffo\",\"text\":\"\",\"type\":\"unstyled\",\"depth\":0,\"inlineStyleRanges\":[],\"entityRanges\":[],\"data\":{}},{\"key\":\"8kpm4\",\"text\":\" \",\"type\":\"atomic\",\"depth\":0,\"inlineStyleRanges\":[],\"entityRanges\":[{\"offset\":0,\"length\":1,\"key\":0}],\"data\":{}},{\"key\":\"b1g62\",\"text\":\"\",\"type\":\"unstyled\",\"depth\":0,\"inlineStyleRanges\":[],\"entityRanges\":[],\"data\":{}},{\"key\":\"69s70\",\"text\":\" \",\"type\":\"atomic\",\"depth\":0,\"inlineStyleRanges\":[],\"entityRanges\":[{\"offset\":0,\"length\":1,\"key\":1}],\"data\":{}},{\"key\":\"1avts\",\"text\":\"\",\"type\":\"unstyled\",\"depth\":0,\"inlineStyleRanges\":[],\"entityRanges\":[],\"data\":{}}],\"entityMap\":{}}",
        "created_at": "2021-04-14T11:10:17.116172Z",
        "published": false,
        "featured": false,
        "banner_link": "https://source.unsplash.com/random",
        "font_banner": "Lorem ipsum dolor sit amet"
    },
    {
        "id": 7,
        "title": "Lorem ipsum dolor sit amet",
        "path": "lorem-ipsum-dolor-sit-amet-7",
        "content": "{\"blocks\":[{\"key\":\"7pffo\",\"text\":\"\",\"type\":\"unstyled\",\"depth\":0,\"inlineStyleRanges\":[],\"entityRanges\":[],\"data\":{}},{\"key\":\"8kpm4\",\"text\":\" \",\"type\":\"atomic\",\"depth\":0,\"inlineStyleRanges\":[],\"entityRanges\":[{\"offset\":0,\"length\":1,\"key\":0}],\"data\":{}},{\"key\":\"b1g62\",\"text\":\"\",\"type\":\"unstyled\",\"depth\":0,\"inlineStyleRanges\":[],\"entityRanges\":[],\"data\":{}},{\"key\":\"69s70\",\"text\":\" \",\"type\":\"atomic\",\"depth\":0,\"inlineStyleRanges\":[],\"entityRanges\":[{\"offset\":0,\"length\":1,\"key\":1}],\"data\":{}},{\"key\":\"1avts\",\"text\":\"\",\"type\":\"unstyled\",\"depth\":0,\"inlineStyleRanges\":[],\"entityRanges\":[],\"data\":{}}],\"entityMap\":{}}",
        "created_at": "2021-04-14T11:10:17.116172Z",
        "published": false,
        "featured": false,
        "banner_link": "https://source.unsplash.com/random",
        "font_banner": "Lorem ipsum dolor sit amet"
    },
    {
        "id": 8,
        "title": "Lorem ipsum dolor sit amet",
        "path": "lorem-ipsum-dolor-sit-amet-8",
        "content": "{\"blocks\":[{\"key\":\"7pffo\",\"text\":\"\",\"type\":\"unstyled\",\"depth\":0,\"inlineStyleRanges\":[],\"entityRanges\":[],\"data\":{}},{\"key\":\"8kpm4\",\"text\":\" \",\"type\":\"atomic\",\"depth\":0,\"inlineStyleRanges\":[],\"entityRanges\":[{\"offset\":0,\"length\":1,\"key\":0}],\"data\":{}},{\"key\":\"b1g62\",\"text\":\"\",\"type\":\"unstyled\",\"depth\":0,\"inlineStyleRanges\":[],\"entityRanges\":[],\"data\":{}},{\"key\":\"69s70\",\"text\":\" \",\"type\":\"atomic\",\"depth\":0,\"inlineStyleRanges\":[],\"entityRanges\":[{\"offset\":0,\"length\":1,\"key\":1}],\"data\":{}},{\"key\":\"1avts\",\"text\":\"\",\"type\":\"unstyled\",\"depth\":0,\"inlineStyleRanges\":[],\"entityRanges\":[],\"data\":{}}],\"entityMap\":{}}",
        "created_at": "2021-04-14T11:10:17.116172Z",
        "published": false,
        "featured": false,
        "banner_link": "https://source.unsplash.com/random",
        "font_banner": "Lorem ipsum dolor sit amet"
    },
    {
        "id": 9,
        "title": "Lorem ipsum dolor sit amet",
        "path": "lorem-ipsum-dolor-sit-amet-9",
        "content": "{\"blocks\":[{\"key\":\"7pffo\",\"text\":\"\",\"type\":\"unstyled\",\"depth\":0,\"inlineStyleRanges\":[],\"entityRanges\":[],\"data\":{}},{\"key\":\"8kpm4\",\"text\":\" \",\"type\":\"atomic\",\"depth\":0,\"inlineStyleRanges\":[],\"entityRanges\":[{\"offset\":0,\"length\":1,\"key\":0}],\"data\":{}},{\"key\":\"b1g62\",\"text\":\"\",\"type\":\"unstyled\",\"depth\":0,\"inlineStyleRanges\":[],\"entityRanges\":[],\"data\":{}},{\"key\":\"69s70\",\"text\":\" \",\"type\":\"atomic\",\"depth\":0,\"inlineStyleRanges\":[],\"entityRanges\":[{\"offset\":0,\"length\":1,\"key\":1}],\"data\":{}},{\"key\":\"1avts\",\"text\":\"\",\"type\":\"unstyled\",\"depth\":0,\"inlineStyleRanges\":[],\"entityRanges\":[],\"data\":{}}],\"entityMap\":{}}",
        "created_at": "2021-04-14T11:10:17.116172Z",
        "published": false,
        "featured": false,
        "banner_link": "https://source.unsplash.com/random",
        "font_banner": "Lorem ipsum dolor sit amet"
    },
    {
        "id": 10,
        "title": "Lorem ipsum dolor sit amet",
        "path": "lorem-ipsum-dolor-sit-amet-10",
        "content": "{\"blocks\":[{\"key\":\"7pffo\",\"text\":\"\",\"type\":\"unstyled\",\"depth\":0,\"inlineStyleRanges\":[],\"entityRanges\":[],\"data\":{}},{\"key\":\"8kpm4\",\"text\":\" \",\"type\":\"atomic\",\"depth\":0,\"inlineStyleRanges\":[],\"entityRanges\":[{\"offset\":0,\"length\":1,\"key\":0}],\"data\":{}},{\"key\":\"b1g62\",\"text\":\"\",\"type\":\"unstyled\",\"depth\":0,\"inlineStyleRanges\":[],\"entityRanges\":[],\"data\":{}},{\"key\":\"69s70\",\"text\":\" \",\"type\":\"atomic\",\"depth\":0,\"inlineStyleRanges\":[],\"entityRanges\":[{\"offset\":0,\"length\":1,\"key\":1}],\"data\":{}},{\"key\":\"1avts\",\"text\":\"\",\"type\":\"unstyled\",\"depth\":0,\"inlineStyleRanges\":[],\"entityRanges\":[],\"data\":{}}],\"entityMap\":{}}",
        "created_at": "2021-04-14T11:10:17.116172Z",
        "published": false,
        "featured": false,
        "banner_link": "https://source.unsplash.com/random",
        "font_banner": "Lorem ipsum dolor sit amet"
    },
    {
        "id": 12,
        "title": "Lorem ipsum dolor sit amet",
        "path": "lorem-ipsum-dolor-sit-amet-11",
        "content": "{\"blocks\":[{\"key\":\"7pffo\",\"text\":\"\",\"type\":\"unstyled\",\"depth\":0,\"inlineStyleRanges\":[],\"entityRanges\":[],\"data\":{}},{\"key\":\"8kpm4\",\"text\":\" \",\"type\":\"atomic\",\"depth\":0,\"inlineStyleRanges\":[],\"entityRanges\":[{\"offset\":0,\"length\":1,\"key\":0}],\"data\":{}},{\"key\":\"b1g62\",\"text\":\"\",\"type\":\"unstyled\",\"depth\":0,\"inlineStyleRanges\":[],\"entityRanges\":[],\"data\":{}},{\"key\":\"69s70\",\"text\":\" \",\"type\":\"atomic\",\"depth\":0,\"inlineStyleRanges\":[],\"entityRanges\":[{\"offset\":0,\"length\":1,\"key\":1}],\"data\":{}},{\"key\":\"1avts\",\"text\":\"\",\"type\":\"unstyled\",\"depth\":0,\"inlineStyleRanges\":[],\"entityRanges\":[],\"data\":{}}],\"entityMap\":{}}",
        "created_at": "2021-04-14T11:10:17.116172Z",
        "published": false,
        "featured": false,
        "banner_link": "https://source.unsplash.com/random",
        "font_banner": "Lorem ipsum dolor sit amet"
    },
    {
        "id": 13,
        "title": "Lorem ipsum dolor sit amet",
        "path": "lorem-ipsum-dolor-sit-amet-13",
        "content": "{\"blocks\":[{\"key\":\"7pffo\",\"text\":\"\",\"type\":\"unstyled\",\"depth\":0,\"inlineStyleRanges\":[],\"entityRanges\":[],\"data\":{}},{\"key\":\"8kpm4\",\"text\":\" \",\"type\":\"atomic\",\"depth\":0,\"inlineStyleRanges\":[],\"entityRanges\":[{\"offset\":0,\"length\":1,\"key\":0}],\"data\":{}},{\"key\":\"b1g62\",\"text\":\"\",\"type\":\"unstyled\",\"depth\":0,\"inlineStyleRanges\":[],\"entityRanges\":[],\"data\":{}},{\"key\":\"69s70\",\"text\":\" \",\"type\":\"atomic\",\"depth\":0,\"inlineStyleRanges\":[],\"entityRanges\":[{\"offset\":0,\"length\":1,\"key\":1}],\"data\":{}},{\"key\":\"1avts\",\"text\":\"\",\"type\":\"unstyled\",\"depth\":0,\"inlineStyleRanges\":[],\"entityRanges\":[],\"data\":{}}],\"entityMap\":{}}",
        "created_at": "2021-04-14T11:10:17.116172Z",
        "published": false,
        "featured": false,
        "banner_link": "https://source.unsplash.com/random",
        "font_banner": "Lorem ipsum dolor sit amet"
    },
    {
        "id": 14,
        "title": "Lorem ipsum dolor sit amet",
        "path": "lorem-ipsum-dolor-sit-amet-14",
        "content": "{\"blocks\":[{\"key\":\"7pffo\",\"text\":\"\",\"type\":\"unstyled\",\"depth\":0,\"inlineStyleRanges\":[],\"entityRanges\":[],\"data\":{}},{\"key\":\"8kpm4\",\"text\":\" \",\"type\":\"atomic\",\"depth\":0,\"inlineStyleRanges\":[],\"entityRanges\":[{\"offset\":0,\"length\":1,\"key\":0}],\"data\":{}},{\"key\":\"b1g62\",\"text\":\"\",\"type\":\"unstyled\",\"depth\":0,\"inlineStyleRanges\":[],\"entityRanges\":[],\"data\":{}},{\"key\":\"69s70\",\"text\":\" \",\"type\":\"atomic\",\"depth\":0,\"inlineStyleRanges\":[],\"entityRanges\":[{\"offset\":0,\"length\":1,\"key\":1}],\"data\":{}},{\"key\":\"1avts\",\"text\":\"\",\"type\":\"unstyled\",\"depth\":0,\"inlineStyleRanges\":[],\"entityRanges\":[],\"data\":{}}],\"entityMap\":{}}",
        "created_at": "2021-04-14T11:10:17.116172Z",
        "published": false,
        "featured": false,
        "banner_link": "https://source.unsplash.com/random",
        "font_banner": "Lorem ipsum dolor sit amet"
    },
    {
        "id": 15,
        "title": "Lorem ipsum dolor sit amet",
        "path": "lorem-ipsum-dolor-sit-amet-15",
        "content": "{\"blocks\":[{\"key\":\"7pffo\",\"text\":\"\",\"type\":\"unstyled\",\"depth\":0,\"inlineStyleRanges\":[],\"entityRanges\":[],\"data\":{}},{\"key\":\"8kpm4\",\"text\":\" \",\"type\":\"atomic\",\"depth\":0,\"inlineStyleRanges\":[],\"entityRanges\":[{\"offset\":0,\"length\":1,\"key\":0}],\"data\":{}},{\"key\":\"b1g62\",\"text\":\"\",\"type\":\"unstyled\",\"depth\":0,\"inlineStyleRanges\":[],\"entityRanges\":[],\"data\":{}},{\"key\":\"69s70\",\"text\":\" \",\"type\":\"atomic\",\"depth\":0,\"inlineStyleRanges\":[],\"entityRanges\":[{\"offset\":0,\"length\":1,\"key\":1}],\"data\":{}},{\"key\":\"1avts\",\"text\":\"\",\"type\":\"unstyled\",\"depth\":0,\"inlineStyleRanges\":[],\"entityRanges\":[],\"data\":{}}],\"entityMap\":{}}",
        "created_at": "2021-04-14T11:10:17.116172Z",
        "published": false,
        "featured": false,
        "banner_link": "https://source.unsplash.com/random",
        "font_banner": "Lorem ipsum dolor sit amet"
    }
]
